AUTHORS
CHANGELOG
COPYING
MANIFEST.in
README.rst
setup.cfg
setup.py
awslogs/__init__.py
awslogs/_version.py
awslogs/bin.py
awslogs/core.py
awslogs/exceptions.py
awslogs_v2.egg-info/PKG-INFO
awslogs_v2.egg-info/SOURCES.txt
awslogs_v2.egg-info/dependency_links.txt
awslogs_v2.egg-info/entry_points.txt
awslogs_v2.egg-info/not-zip-safe
awslogs_v2.egg-info/requires.txt
awslogs_v2.egg-info/top_level.txt
tests/__init__.py
tests/test_it.py
tests/test_versions.py